{
  "textures": [
    {
      "image": "116.png",
      "format": "RGBA8888",
      "size": {
        "w": 3770,
        "h": 3077
      },
      "scale": 1,
      "frames": [
        {
          "filename": "0000.png",
          "rotated": false,
          "trimmed": true,
          "sourceSize": {
            "w": 900,
            "h": 900
          },
          "spriteSourceSize": {
            "x": 246,
            "y": 203,
            "w": 295,
            "h": 451
          },
          "frame": {
            "x": 1,
            "y": 1,
            "w": 295,
            "h": 451
          }
        },
        {
          "filename": "0001.png",
          "rotated": false,
          "trimmed": true,
          "sourceSize": {
            "w": 900,
            "h": 900
          },
          "spriteSourceSize": {
            "x": 246,
            "y": 203,
            "w": 294,
            "h": 451
          },
          "frame": {
            "x": 498,
            "y": 1,
            "w": 294,
            "h": 451
          }
        },
        {
          "filename": "0002.png",
          "rotated": false,
          "trimmed": true,
          "sourceSize": {
            "w": 900,
            "h": 900
          },
          "spriteSourceSize": {
            "x": 246,
            "y": 203,
            "w": 294,
            "h": 451
          },
          "frame": {
            "x": 994,
            "y": 1,
            "w": 294,
            "h": 451
          }
        },
        {
          "filename": "0003.png",
          "rotated": false,
          "trimmed": true,
          "sourceSize": {
            "w": 900,
            "h": 900
          },
          "spriteSourceSize": {
            "x": 246,
            "y": 203,
            "w": 294,
            "h": 451
          },
          "frame": {
            "x": 1490,
            "y": 1,
            "w": 294,
            "h": 451
          }
        },
        {
          "filename": "0004.png",
          "rotated": false,
          "trimmed": true,
          "sourceSize": {
            "w": 900,
            "h": 900
          },
          "spriteSourceSize": {
            "x": 247,
            "y": 203,
            "w": 293,
            "h": 451
          },
          "frame": {
            "x": 1986,
            "y": 1,
            "w": 293,
            "h": 451
          }
        },
        {
          "filename": "0022.png",
          "rotated": false,
          "trimmed": true,
          "sourceSize": {
            "w": 900,
            "h": 900
          },
          "spriteSourceSize": {
            "x": 246,
            "y": 203,
            "w": 295,
            "h": 451
          },
          "frame": {
            "x": 2481,
            "y": 1,
            "w": 295,
            "h": 451
          }
        },
        {
          "filename": "0023.png",
          "rotated": false,
          "trimmed": true,
          "sourceSize": {
            "w": 900,
            "h": 900
          },
          "spriteSourceSize": {
            "x": 246,
            "y": 203,
            "w": 295,
            "h": 451
          },
          "frame": {
            "x": 2978,
            "y": 1,
            "w": 295,
            "h": 451
          }
        },
        {
          "filename": "0025.png",
          "rotated": false,
          "trimmed": true,
          "sourceSize": {
            "w": 900,
            "h": 900
          },
          "spriteSourceSize": {
            "x": 246,
            "y": 203,
            "w": 294,
            "h": 451
          },
          "frame": {
            "x": 3475,
            "y": 1,
            "w": 294,
            "h": 451
          }
        },
        {
          "filename": "0024.png",
          "rotated": false,
          "trimmed": true,
          "sourceSize": {
            "w": 900,
            "h": 900
          },
          "spriteSourceSize": {
            "x": 246,
            "y": 203,
            "w": 295,
            "h": 451
          },
          "frame": {
            "x": 1,
            "y": 654,
            "w": 295,
            "h": 451
          }
        },
        {
          "filename": "0026.png",
          "rotated": false,
          "trimmed": true,
          "sourceSize": {
            "w": 900,
            "h": 900
          },
          "spriteSourceSize": {
            "x": 246,
            "y": 203,
            "w": 294,
            "h": 451
          },
          "frame": {
            "x": 498,
            "y": 654,
            "w": 294,
            "h": 451
          }
        },
        {
          "filename": "0027.png",
          "rotated": false,
          "trimmed": true,
          "sourceSize": {
            "w": 900,
            "h": 900
          },
          "spriteSourceSize": {
            "x": 246,
            "y": 203,
            "w": 294,
            "h": 451
          },
          "frame": {
            "x": 994,
            "y": 654,
            "w": 294,
            "h": 451
          }
        },
        {
          "filename": "0028.png",
          "rotated": false,
          "trimmed": true,
          "sourceSize": {
            "w": 900,
            "h": 900
          },
          "spriteSourceSize": {
            "x": 247,
            "y": 203,
            "w": 293,
            "h": 451
          },
          "frame": {
            "x": 1490,
            "y": 654,
            "w": 293,
            "h": 451
          }
        },
        {
          "filename": "0005.png",
          "rotated": false,
          "trimmed": true,
          "sourceSize": {
            "w": 900,
            "h": 900
          },
          "spriteSourceSize": {
            "x": 247,
            "y": 202,
            "w": 294,
            "h": 452
          },
          "frame": {
            "x": 1985,
            "y": 654,
            "w": 294,
            "h": 452
          }
        },
        {
          "filename": "0006.png",
          "rotated": false,
          "trimmed": true,
          "sourceSize": {
            "w": 900,
            "h": 900
          },
          "spriteSourceSize": {
            "x": 247,
            "y": 202,
            "w": 294,
            "h": 452
          },
          "frame": {
            "x": 2481,
            "y": 654,
            "w": 294,
            "h": 452
          }
        },
        {
          "filename": "0020.png",
          "rotated": false,
          "trimmed": true,
          "sourceSize": {
            "w": 900,
            "h": 900
          },
          "spriteSourceSize": {
            "x": 246,
            "y": 202,
            "w": 295,
            "h": 452
          },
          "frame": {
            "x": 2977,
            "y": 654,
            "w": 295,
            "h": 452
          }
        },
        {
          "filename": "0021.png",
          "rotated": false,
          "trimmed": true,
          "sourceSize": {
            "w": 900,
            "h": 900
          },
          "spriteSourceSize": {
            "x": 246,
            "y": 202,
            "w": 295,
            "h": 452
          },
          "frame": {
            "x": 3474,
            "y": 654,
            "w": 295,
            "h": 452
          }
        },
        {
          "filename": "0029.png",
          "rotated": false,
          "trimmed": true,
          "sourceSize": {
            "w": 900,
            "h": 900
          },
          "spriteSourceSize": {
            "x": 247,
            "y": 202,
            "w": 294,
            "h": 452
          },
          "frame": {
            "x": 1,
            "y": 1307,
            "w": 294,
            "h": 452
          }
        },
        {
          "filename": "0030.png",
          "rotated": false,
          "trimmed": true,
          "sourceSize": {
            "w": 900,
            "h": 900
          },
          "spriteSourceSize": {
            "x": 247,
            "y": 202,
            "w": 294,
            "h": 452
          },
          "frame": {
            "x": 497,
            "y": 1307,
            "w": 294,
            "h": 452
          }
        },
        {
          "filename": "0007.png",
          "rotated": false,
          "trimmed": true,
          "sourceSize": {
            "w": 900,
            "h": 900
          },
          "spriteSourceSize": {
            "x": 248,
            "y": 201,
            "w": 293,
            "h": 453
          },
          "frame": {
            "x": 993,
            "y": 1307,
            "w": 293,
            "h": 453
          }
        },
        {
          "filename": "0018.png",
          "rotated": false,
          "trimmed": true,
          "sourceSize": {
            "w": 900,
            "h": 900
          },
          "spriteSourceSize": {
            "x": 247,
            "y": 201,
            "w": 295,
            "h": 453
          },
          "frame": {
            "x": 1488,
            "y": 1307,
            "w": 295,
            "h": 453
          }
        },
        {
          "filename": "0019.png",
          "rotated": false,
          "trimmed": true,
          "sourceSize": {
            "w": 900,
            "h": 900
          },
          "spriteSourceSize": {
            "x": 247,
            "y": 201,
            "w": 295,
            "h": 453
          },
          "frame": {
            "x": 1985,
            "y": 1308,
            "w": 295,
            "h": 453
          }
        },
        {
          "filename": "0031.png",
          "rotated": false,
          "trimmed": true,
          "sourceSize": {
            "w": 900,
            "h": 900
          },
          "spriteSourceSize": {
            "x": 248,
            "y": 201,
            "w": 293,
            "h": 453
          },
          "frame": {
            "x": 2482,
            "y": 1308,
            "w": 293,
            "h": 453
          }
        },
        {
          "filename": "0008.png",
          "rotated": false,
          "trimmed": true,
          "sourceSize": {
            "w": 900,
            "h": 900
          },
          "spriteSourceSize": {
            "x": 248,
            "y": 200,
            "w": 293,
            "h": 454
          },
          "frame": {
            "x": 2977,
            "y": 1308,
            "w": 293,
            "h": 454
          }
        },
        {
          "filename": "0009.png",
          "rotated": false,
          "trimmed": true,
          "sourceSize": {
            "w": 900,
            "h": 900
          },
          "spriteSourceSize": {
            "x": 248,
            "y": 200,
            "w": 293,
            "h": 454
          },
          "frame": {
            "x": 3472,
            "y": 1308,
            "w": 293,
            "h": 454
          }
        },
        {
          "filename": "0016.png",
          "rotated": false,
          "trimmed": true,
          "sourceSize": {
            "w": 900,
            "h": 900
          },
          "spriteSourceSize": {
            "x": 247,
            "y": 200,
            "w": 295,
            "h": 454
          },
          "frame": {
            "x": 1,
            "y": 1961,
            "w": 295,
            "h": 454
          }
        },
        {
          "filename": "0032.png",
          "rotated": false,
          "trimmed": true,
          "sourceSize": {
            "w": 900,
            "h": 900
          },
          "spriteSourceSize": {
            "x": 248,
            "y": 200,
            "w": 293,
            "h": 454
          },
          "frame": {
            "x": 498,
            "y": 1961,
            "w": 293,
            "h": 454
          }
        },
        {
          "filename": "0017.png",
          "rotated": false,
          "trimmed": true,
          "sourceSize": {
            "w": 900,
            "h": 900
          },
          "spriteSourceSize": {
            "x": 247,
            "y": 200,
            "w": 295,
            "h": 454
          },
          "frame": {
            "x": 993,
            "y": 1962,
            "w": 295,
            "h": 454
          }
        },
        {
          "filename": "0033.png",
          "rotated": false,
          "trimmed": true,
          "sourceSize": {
            "w": 900,
            "h": 900
          },
          "spriteSourceSize": {
            "x": 248,
            "y": 200,
            "w": 293,
            "h": 454
          },
          "frame": {
            "x": 1490,
            "y": 1962,
            "w": 293,
            "h": 454
          }
        },
        {
          "filename": "0010.png",
          "rotated": false,
          "trimmed": true,
          "sourceSize": {
            "w": 900,
            "h": 900
          },
          "spriteSourceSize": {
            "x": 248,
            "y": 199,
            "w": 294,
            "h": 455
          },
          "frame": {
            "x": 1985,
            "y": 1963,
            "w": 294,
            "h": 455
          }
        },
        {
          "filename": "0011.png",
          "rotated": false,
          "trimmed": true,
          "sourceSize": {
            "w": 900,
            "h": 900
          },
          "spriteSourceSize": {
            "x": 249,
            "y": 199,
            "w": 293,
            "h": 455
          },
          "frame": {
            "x": 2481,
            "y": 1963,
            "w": 293,
            "h": 455
          }
        },
        {
          "filename": "0012.png",
          "rotated": false,
          "trimmed": true,
          "sourceSize": {
            "w": 900,
            "h": 900
          },
          "spriteSourceSize": {
            "x": 249,
            "y": 199,
            "w": 293,
            "h": 455
          },
          "frame": {
            "x": 2976,
            "y": 1964,
            "w": 293,
            "h": 455
          }
        },
        {
          "filename": "0013.png",
          "rotated": false,
          "trimmed": true,
          "sourceSize": {
            "w": 900,
            "h": 900
          },
          "spriteSourceSize": {
            "x": 248,
            "y": 199,
            "w": 294,
            "h": 455
          },
          "frame": {
            "x": 3471,
            "y": 1964,
            "w": 294,
            "h": 455
          }
        },
        {
          "filename": "0014.png",
          "rotated": false,
          "trimmed": true,
          "sourceSize": {
            "w": 900,
            "h": 900
          },
          "spriteSourceSize": {
            "x": 248,
            "y": 199,
            "w": 294,
            "h": 455
          },
          "frame": {
            "x": 1,
            "y": 2617,
            "w": 294,
            "h": 455
          }
        },
        {
          "filename": "0015.png",
          "rotated": false,
          "trimmed": true,
          "sourceSize": {
            "w": 900,
            "h": 900
          },
          "spriteSourceSize": {
            "x": 248,
            "y": 199,
            "w": 294,
            "h": 455
          },
          "frame": {
            "x": 497,
            "y": 2617,
            "w": 294,
            "h": 455
          }
        },
        {
          "filename": "0034.png",
          "rotated": false,
          "trimmed": true,
          "sourceSize": {
            "w": 900,
            "h": 900
          },
          "spriteSourceSize": {
            "x": 248,
            "y": 199,
            "w": 294,
            "h": 455
          },
          "frame": {
            "x": 993,
            "y": 2618,
            "w": 294,
            "h": 455
          }
        },
        {
          "filename": "0035.png",
          "rotated": false,
          "trimmed": true,
          "sourceSize": {
            "w": 900,
            "h": 900
          },
          "spriteSourceSize": {
            "x": 249,
            "y": 199,
            "w": 293,
            "h": 455
          },
          "frame": {
            "x": 1489,
            "y": 2618,
            "w": 293,
            "h": 455
          }
        },
        {
          "filename": "0036.png",
          "rotated": false,
          "trimmed": true,
          "sourceSize": {
            "w": 900,
            "h": 900
          },
          "spriteSourceSize": {
            "x": 249,
            "y": 199,
            "w": 293,
            "h": 455
          },
          "frame": {
            "x": 1984,
            "y": 2620,
            "w": 293,
            "h": 455
          }
        },
        {
          "filename": "0037.png",
          "rotated": false,
          "trimmed": true,
          "sourceSize": {
            "w": 900,
            "h": 900
          },
          "spriteSourceSize": {
            "x": 248,
            "y": 199,
            "w": 294,
            "h": 455
          },
          "frame": {
            "x": 2479,
            "y": 2620,
            "w": 294,
            "h": 455
          }
        },
        {
          "filename": "0038.png",
          "rotated": false,
          "trimmed": true,
          "sourceSize": {
            "w": 900,
            "h": 900
          },
          "spriteSourceSize": {
            "x": 248,
            "y": 199,
            "w": 294,
            "h": 455
          },
          "frame": {
            "x": 2975,
            "y": 2621,
            "w": 294,
            "h": 455
          }
        },
        {
          "filename": "0039.png",
          "rotated": false,
          "trimmed": true,
          "sourceSize": {
            "w": 900,
            "h": 900
          },
          "spriteSourceSize": {
            "x": 248,
            "y": 199,
            "w": 294,
            "h": 455
          },
          "frame": {
            "x": 3471,
            "y": 2621,
            "w": 294,
            "h": 455
          }
        }
      ]
    }
  ],
  "meta": {
    "app": "https://www.codeandweb.com/texturepacker",
    "version": "3.0",
    "smartupdate": "$TexturePacker:SmartUpdate:c00c296319bf25f5d4eede52cda3fd2b:a2b211e7282fe9b524a928a6f53f0725:c1ad22c6b4af4687b962dc77926d3fce$"
  }
}