{
  "textures": [
    {
      "image": "60.png",
      "format": "RGBA8888",
      "size": {
        "w": 1772,
        "h": 2706
      },
      "scale": 1,
      "frames": [
        {
          "filename": "0001.png",
          "rotated": false,
          "trimmed": true,
          "sourceSize": {
            "w": 900,
            "h": 901
          },
          "spriteSourceSize": {
            "x": 170,
            "y": 248,
            "w": 362,
            "h": 404
          },
          "frame": {
            "x": 1,
            "y": 1,
            "w": 362,
            "h": 404
          }
        },
        {
          "filename": "0003.png",
          "rotated": false,
          "trimmed": true,
          "sourceSize": {
            "w": 900,
            "h": 901
          },
          "spriteSourceSize": {
            "x": 232,
            "y": 332,
            "w": 337,
            "h": 320
          },
          "frame": {
            "x": 565,
            "y": 1,
            "w": 337,
            "h": 320
          }
        },
        {
          "filename": "0002.png",
          "rotated": false,
          "trimmed": true,
          "sourceSize": {
            "w": 900,
            "h": 901
          },
          "spriteSourceSize": {
            "x": 205,
            "y": 282,
            "w": 334,
            "h": 370
          },
          "frame": {
            "x": 1104,
            "y": 1,
            "w": 334,
            "h": 370
          }
        },
        {
          "filename": "0000.png",
          "rotated": false,
          "trimmed": true,
          "sourceSize": {
            "w": 900,
            "h": 901
          },
          "spriteSourceSize": {
            "x": 345,
            "y": 0,
            "w": 120,
            "h": 69
          },
          "frame": {
            "x": 1640,
            "y": 1,
            "w": 120,
            "h": 69
          }
        },
        {
          "filename": "0006.png",
          "rotated": false,
          "trimmed": true,
          "sourceSize": {
            "w": 900,
            "h": 901
          },
          "spriteSourceSize": {
            "x": 247,
            "y": 346,
            "w": 310,
            "h": 364
          },
          "frame": {
            "x": 565,
            "y": 523,
            "w": 310,
            "h": 364
          }
        },
        {
          "filename": "0007.png",
          "rotated": false,
          "trimmed": true,
          "sourceSize": {
            "w": 900,
            "h": 901
          },
          "spriteSourceSize": {
            "x": 251,
            "y": 326,
            "w": 305,
            "h": 382
          },
          "frame": {
            "x": 1,
            "y": 607,
            "w": 305,
            "h": 382
          }
        },
        {
          "filename": "0005.png",
          "rotated": false,
          "trimmed": true,
          "sourceSize": {
            "w": 900,
            "h": 901
          },
          "spriteSourceSize": {
            "x": 252,
            "y": 365,
            "w": 305,
            "h": 326
          },
          "frame": {
            "x": 1077,
            "y": 573,
            "w": 305,
            "h": 326
          }
        },
        {
          "filename": "0008.png",
          "rotated": false,
          "trimmed": true,
          "sourceSize": {
            "w": 900,
            "h": 901
          },
          "spriteSourceSize": {
            "x": 251,
            "y": 314,
            "w": 304,
            "h": 376
          },
          "frame": {
            "x": 508,
            "y": 1089,
            "w": 304,
            "h": 376
          }
        },
        {
          "filename": "0004.png",
          "rotated": false,
          "trimmed": true,
          "sourceSize": {
            "w": 900,
            "h": 901
          },
          "spriteSourceSize": {
            "x": 259,
            "y": 362,
            "w": 298,
            "h": 291
          },
          "frame": {
            "x": 1,
            "y": 1191,
            "w": 298,
            "h": 291
          }
        },
        {
          "filename": "0015.png",
          "rotated": false,
          "trimmed": true,
          "sourceSize": {
            "w": 900,
            "h": 901
          },
          "spriteSourceSize": {
            "x": 347,
            "y": 254,
            "w": 296,
            "h": 398
          },
          "frame": {
            "x": 1014,
            "y": 1101,
            "w": 296,
            "h": 398
          }
        },
        {
          "filename": "0012.png",
          "rotated": false,
          "trimmed": true,
          "sourceSize": {
            "w": 900,
            "h": 901
          },
          "spriteSourceSize": {
            "x": 350,
            "y": 249,
            "w": 259,
            "h": 403
          },
          "frame": {
            "x": 1512,
            "y": 1101,
            "w": 259,
            "h": 403
          }
        },
        {
          "filename": "0016.png",
          "rotated": false,
          "trimmed": true,
          "sourceSize": {
            "w": 900,
            "h": 901
          },
          "spriteSourceSize": {
            "x": 349,
            "y": 253,
            "w": 294,
            "h": 399
          },
          "frame": {
            "x": 501,
            "y": 1667,
            "w": 294,
            "h": 399
          }
        },
        {
          "filename": "0017.png",
          "rotated": false,
          "trimmed": true,
          "sourceSize": {
            "w": 900,
            "h": 901
          },
          "spriteSourceSize": {
            "x": 350,
            "y": 252,
            "w": 293,
            "h": 400
          },
          "frame": {
            "x": 1,
            "y": 1684,
            "w": 293,
            "h": 400
          }
        },
        {
          "filename": "0018.png",
          "rotated": false,
          "trimmed": true,
          "sourceSize": {
            "w": 900,
            "h": 901
          },
          "spriteSourceSize": {
            "x": 350,
            "y": 252,
            "w": 293,
            "h": 400
          },
          "frame": {
            "x": 997,
            "y": 1701,
            "w": 293,
            "h": 400
          }
        },
        {
          "filename": "0013.png",
          "rotated": false,
          "trimmed": true,
          "sourceSize": {
            "w": 900,
            "h": 901
          },
          "spriteSourceSize": {
            "x": 350,
            "y": 253,
            "w": 277,
            "h": 399
          },
          "frame": {
            "x": 1492,
            "y": 1706,
            "w": 277,
            "h": 399
          }
        },
        {
          "filename": "0009.png",
          "rotated": false,
          "trimmed": true,
          "sourceSize": {
            "w": 900,
            "h": 901
          },
          "spriteSourceSize": {
            "x": 262,
            "y": 294,
            "w": 292,
            "h": 382
          },
          "frame": {
            "x": 496,
            "y": 2268,
            "w": 292,
            "h": 382
          }
        },
        {
          "filename": "0014.png",
          "rotated": false,
          "trimmed": true,
          "sourceSize": {
            "w": 900,
            "h": 901
          },
          "spriteSourceSize": {
            "x": 347,
            "y": 255,
            "w": 290,
            "h": 397
          },
          "frame": {
            "x": 1,
            "y": 2286,
            "w": 290,
            "h": 397
          }
        },
        {
          "filename": "0011.png",
          "rotated": false,
          "trimmed": true,
          "sourceSize": {
            "w": 900,
            "h": 901
          },
          "spriteSourceSize": {
            "x": 320,
            "y": 254,
            "w": 259,
            "h": 398
          },
          "frame": {
            "x": 990,
            "y": 2307,
            "w": 259,
            "h": 398
          }
        },
        {
          "filename": "0010.png",
          "rotated": false,
          "trimmed": true,
          "sourceSize": {
            "w": 900,
            "h": 901
          },
          "spriteSourceSize": {
            "x": 284,
            "y": 272,
            "w": 269,
            "h": 389
          },
          "frame": {
            "x": 1451,
            "y": 2307,
            "w": 269,
            "h": 389
          }
        }
      ]
    }
  ],
  "meta": {
    "app": "https://www.codeandweb.com/texturepacker",
    "version": "3.0",
    "smartupdate": "$TexturePacker:SmartUpdate:419c04cb3dffc10e25cee7cbf812ae4e:6ff9e73e1742e80d2aaccf80f3fc5013:1b9c61013f1623e5f822b4ae46d80c1e$"
  }
}